{
    "Piccolo SP": {
        "EquipmentSlots": 2,
        "Level": 1,
        "OtherSoulBoost": {
            "Crit": 1,
            "Ki": 1
        },
        "OtherUserStats": {
            "Crit": 1,
            "Ki": 1
        },
        "SoulBoost": {
            "BATK": 1,
            "BDEF": 1,
            "HP": 1,
            "SATK": 1,
            "SDEF": 1
        },
        "Stars": 1,
        "UserStats": {
            "BATK": 1,
            "BDEF": 1,
            "HP": 1,
            "SATK": 1,
            "SDEF": 1
        },
        "_BaseStats": {
            "BATK": -1,
            "BDEF": -1,
            "HP": -1,
            "SATK": -1,
            "SDEF": -1
        },
        "_OtherBaseStats": {
            "Crit": -1,
            "Ki": -1
        },
        "_Power": 24,
        "_Tags": []
    },
    "Vegeta SP": {
        "EquipmentSlots": 1,
        "Level": 2,
        "OtherSoulBoost": {
            "Crit": 3,
            "Ki": 2
        },
        "OtherUserStats": {
            "Crit": 3,
            "Ki": 2
        },
        "SoulBoost": {
            "BATK": 3,
            "BDEF": 2,
            "HP": 3,
            "SATK": 2,
            "SDEF": 3
        },
        "Stars": 2,
        "UserStats": {
            "BATK": 3,
            "BDEF": 2,
            "HP": 3,
            "SATK": 2,
            "SDEF": 3
        },
        "_BaseStats": {
            "BATK": -1,
            "BDEF": -1,
            "HP": -1,
            "SATK": -1,
            "SDEF": -1
        },
        "_OtherBaseStats": {
            "Crit": -1,
            "Ki": -1
        },
        "_Power": 50,
        "_Tags": []
    }
}